azure/mgmt/eventgrid/__init__.py
azure/mgmt/eventgrid/_configuration.py
azure/mgmt/eventgrid/_event_grid_management_client.py
azure/mgmt/eventgrid/_patch.py
azure/mgmt/eventgrid/_vendor.py
azure/mgmt/eventgrid/_version.py
azure/mgmt/eventgrid/py.typed
azure/mgmt/eventgrid/aio/__init__.py
azure/mgmt/eventgrid/aio/_configuration.py
azure/mgmt/eventgrid/aio/_event_grid_management_client.py
azure/mgmt/eventgrid/aio/_patch.py
azure/mgmt/eventgrid/aio/operations/__init__.py
azure/mgmt/eventgrid/aio/operations/_channels_operations.py
azure/mgmt/eventgrid/aio/operations/_domain_event_subscriptions_operations.py
azure/mgmt/eventgrid/aio/operations/_domain_topic_event_subscriptions_operations.py
azure/mgmt/eventgrid/aio/operations/_domain_topics_operations.py
azure/mgmt/eventgrid/aio/operations/_domains_operations.py
azure/mgmt/eventgrid/aio/operations/_event_subscriptions_operations.py
azure/mgmt/eventgrid/aio/operations/_extension_topics_operations.py
azure/mgmt/eventgrid/aio/operations/_operations.py
azure/mgmt/eventgrid/aio/operations/_partner_configurations_operations.py
azure/mgmt/eventgrid/aio/operations/_partner_namespaces_operations.py
azure/mgmt/eventgrid/aio/operations/_partner_registrations_operations.py
azure/mgmt/eventgrid/aio/operations/_partner_topic_event_subscriptions_operations.py
azure/mgmt/eventgrid/aio/operations/_partner_topics_operations.py
azure/mgmt/eventgrid/aio/operations/_private_endpoint_connections_operations.py
azure/mgmt/eventgrid/aio/operations/_private_link_resources_operations.py
azure/mgmt/eventgrid/aio/operations/_system_topic_event_subscriptions_operations.py
azure/mgmt/eventgrid/aio/operations/_system_topics_operations.py
azure/mgmt/eventgrid/aio/operations/_topic_event_subscriptions_operations.py
azure/mgmt/eventgrid/aio/operations/_topic_types_operations.py
azure/mgmt/eventgrid/aio/operations/_topics_operations.py
azure/mgmt/eventgrid/aio/operations/_verified_partners_operations.py
azure/mgmt/eventgrid/models/__init__.py
azure_mgmt_eventgrid-10.2.0.dist-info/LICENSE
azure_mgmt_eventgrid-10.2.0.dist-info/METADATA
azure_mgmt_eventgrid-10.2.0.dist-info/WHEEL
azure_mgmt_eventgrid-10.2.0.dist-info/top_level.txt
azure_mgmt_eventgrid-10.2.0.dist-info/RECORD
